pymnk/__init__.py
pymnk/mnk.py
pymnk/py.typed
pymnk-0.3.1.dist-info/LICENSE
pymnk-0.3.1.dist-info/METADATA
pymnk-0.3.1.dist-info/WHEEL
pymnk-0.3.1.dist-info/top_level.txt
pymnk-0.3.1.dist-info/RECORD
