Metadata-Version: 2.1
Name: pymnk
Version: 0.3.1
Summary: Python library for k-in-a-row family of games
Author: Zeta Factorial
License: MIT
Project-URL: Homepage, https://github.com/ZetaFactorial/pymnk
Project-URL: Bug Tracker, https://github.com/ZetaFactorial/pymnk/issues
Keywords: tic-tac-toe,gomoku,connect6,pente
Classifier: Development Status :: 4 - Beta
Classifier: Intended Audience :: Developers
Classifier: Intended Audience :: Science/Research
Classifier: License :: OSI Approved :: MIT License
Classifier: Operating System :: OS Independent
Classifier: Programming Language :: Python :: 3.10
Classifier: Topic :: Games/Entertainment :: Board Games
Classifier: Topic :: Games/Entertainment :: Turn Based Strategy
Classifier: Topic :: Software Development :: Libraries :: Python Modules
Classifier: Typing :: Typed
Requires-Python: >=3.10
License-File: LICENSE
